karrot/__init__.py
karrot/client.py
karrot/enums.py
karrot/exceptions.py
karrot/gateway.py
karrot/models.py
karrot/protocol.py
karrot-0.1.1.dist-info/METADATA
karrot-0.1.1.dist-info/WHEEL
karrot-0.1.1.dist-info/licenses/LICENSE
karrot-0.1.1.dist-info/RECORD
