Metadata-Version: 2.4
Name: karrot
Version: 0.1.1
Summary: Discord.py style async library for Karrot chat
Project-URL: Homepage, https://github.com/deongdion/karrot.py
Project-URL: Repository, https://github.com/deongdion/karrot.py
Project-URL: Issues, https://github.com/deongdion/karrot.py/issues
Author: deongdion
License-Expression: MIT
License-File: LICENSE
Keywords: async,chat,daangn,karrot,websocket
Classifier: Development Status :: 3 - Alpha
Classifier: Framework :: AsyncIO
Classifier: Intended Audience :: Developers
Classifier: License :: OSI Approved :: MIT License
Classifier: Operating System :: OS Independent
Classifier: Programming Language :: Python :: 3
Classifier: Programming Language :: Python :: 3.10
Classifier: Programming Language :: Python :: 3.11
Classifier: Programming Language :: Python :: 3.12
Classifier: Programming Language :: Python :: 3.13
Requires-Python: >=3.10
Requires-Dist: aiohttp>=3.8.0
Requires-Dist: websockets>=10.0
